bdt2cpp/Node.py
bdt2cpp/PickleLoader.py
bdt2cpp/TMVAParser.py
bdt2cpp/XGBoostParser.py
bdt2cpp/__init__.py
bdt2cpp/templates/Makefile.template
bdt2cpp/templates/info.template
bdt2cpp/templates/main.cpp.template
bdt2cpp/templates/standalone.function.template
bdt2cpp/templates/tree.function.template
bdt2cpp-0.2.0.data/scripts/bdt2cpp
bdt2cpp-0.2.0.dist-info/LICENSE
bdt2cpp-0.2.0.dist-info/METADATA
bdt2cpp-0.2.0.dist-info/WHEEL
bdt2cpp-0.2.0.dist-info/top_level.txt
bdt2cpp-0.2.0.dist-info/RECORD
