Metadata-Version: 2.1
Name: bdt2cpp
Version: 0.2.0
Summary: Transpile BDTs to C++ code.
Home-page: https://github.com/bixel/bdt2cpp
Author: Kevin Heinicke <kevin@kehei.de>
License: UNKNOWN
Platform: UNKNOWN
Classifier: Development Status :: 3 - Alpha
Classifier: Intended Audience :: Science/Research
Classifier: Topic :: Scientific/Engineering :: Artificial Intelligence
Classifier: Topic :: Scientific/Engineering :: Physics
Classifier: Topic :: Software Development :: Code Generators
Classifier: License :: OSI Approved :: MIT License
Classifier: Programming Language :: Python :: 3.6
Requires-Dist: jinja2
